{"__symbolic":"module","version":4,"metadata":{"AlainErrorCollectConfig":{"__symbolic":"interface"},"AlainImageConfig":{"__symbolic":"interface"},"AlainDateRangePickerConfig":{"__symbolic":"interface"},"AlainDateRangePickerShortcut":{"__symbolic":"interface"},"AlainDateRangePickerShortcutItem":{"__symbolic":"interface"},"AlainLoadingConfig":{"__symbolic":"interface"},"AlainLodopConfig":{"__symbolic":"interface"},"AlainPageHeaderConfig":{"__symbolic":"interface"},"AlainQRConfig":{"__symbolic":"interface"},"AlainSEConfig":{"__symbolic":"interface"},"AlainSVConfig":{"__symbolic":"class","members":{}},"AlainSGConfig":{"__symbolic":"interface"},"AlainSTConfig":{"__symbolic":"interface"},"AlainXlsxConfig":{"__symbolic":"interface"},"AlainZipConfig":{"__symbolic":"interface"},"AlainMediaConfig":{"__symbolic":"interface"},"AlainPdfConfig":{"__symbolic":"interface"},"AlainOnboardingConfig":{"__symbolic":"interface"},"AlainACLConfig":{"__symbolic":"interface"},"AlainACLType":{"__symbolic":"interface"},"AlainAuthConfig":{"__symbolic":"interface"},"AlainCacheConfig":{"__symbolic":"interface"},"AlainChartConfig":{"__symbolic":"interface"},"AlainUtilArrayConfig":{"__symbolic":"interface"},"AlainUtilCurrencyConfig":{"__symbolic":"interface"},"AlainThemeHttpClientConfig":{"__symbolic":"interface"},"AlainThemeResponsiveConfig":{"__symbolic":"interface"},"AlainMockConfig":{"__symbolic":"interface"},"AlainSFConfigFormatMap":{"__symbolic":"interface"},"AlainSFConfig":{"__symbolic":"interface"},"AlainConfig":{"__symbolic":"interface"},"AlainConfigKey":{"__symbolic":"interface"},"ALAIN_CONFIG":{"__symbolic":"new","expression":{"__symbolic":"reference","module":"@angular/core","name":"InjectionToken","line":61,"character":32},"arguments":["alain-config",{"providedIn":"root","factory":{"__symbolic":"reference","name":"ALAIN_CONFIG_FACTORY"}}]},"ALAIN_CONFIG_FACTORY":{"__symbolic":"function","parameters":[],"value":{}},"AlainConfigService":{"__symbolic":"class","decorators":[{"__symbolic":"call","expression":{"__symbolic":"reference","module":"@angular/core","name":"Injectable","line":8,"character":1},"arguments":[{"providedIn":"root"}]}],"members":{"__ctor__":[{"__symbolic":"constructor","parameterDecorators":[[{"__symbolic":"call","expression":{"__symbolic":"reference","module":"@angular/core","name":"Optional","line":12,"character":15}},{"__symbolic":"call","expression":{"__symbolic":"reference","module":"@angular/core","name":"Inject","line":12,"character":27},"arguments":[{"__symbolic":"reference","name":"ALAIN_CONFIG"}]}]],"parameters":[{"__symbolic":"reference","name":"AlainConfig"}]}],"get":[{"__symbolic":"method"}],"merge":[{"__symbolic":"method"}],"attach":[{"__symbolic":"method"}],"attachKey":[{"__symbolic":"method"}],"set":[{"__symbolic":"method"}]},"statics":{"ɵprov":{}}}},"origins":{"AlainErrorCollectConfig":"./abc/error-collect.type","AlainImageConfig":"./abc/image.type","AlainDateRangePickerConfig":"./abc/date-picker.type","AlainDateRangePickerShortcut":"./abc/date-picker.type","AlainDateRangePickerShortcutItem":"./abc/date-picker.type","AlainLoadingConfig":"./abc/loading.type","AlainLodopConfig":"./abc/lodop.type","AlainPageHeaderConfig":"./abc/page-header.type","AlainQRConfig":"./abc/qr.type","AlainSEConfig":"./abc/se.type","AlainSVConfig":"./abc/sv.type","AlainSGConfig":"./abc/sg.type","AlainSTConfig":"./abc/st.type","AlainXlsxConfig":"./abc/xlsx.type","AlainZipConfig":"./abc/zip.type","AlainMediaConfig":"./abc/media.type","AlainPdfConfig":"./abc/pdf.type","AlainOnboardingConfig":"./abc/onboarding.type","AlainACLConfig":"./acl/acl.type","AlainACLType":"./acl/acl.type","AlainAuthConfig":"./auth/auth.type","AlainCacheConfig":"./cache/cache.type","AlainChartConfig":"./chart/chart.type","AlainUtilArrayConfig":"./util/array.type","AlainUtilCurrencyConfig":"./util/currency.type","AlainThemeHttpClientConfig":"./theme/http.type","AlainThemeResponsiveConfig":"./theme/responsive.type","AlainMockConfig":"./mock/mock.type","AlainSFConfigFormatMap":"./sf/sf.type","AlainSFConfig":"./sf/sf.type","AlainConfig":"./config.types","AlainConfigKey":"./config.types","ALAIN_CONFIG":"./config.types","ALAIN_CONFIG_FACTORY":"./config.types","AlainConfigService":"./config.service"},"importAs":"@delon/util/config"}